skillpacks/__init__.py
skillpacks/action_opts.py
skillpacks/auth/default.py
skillpacks/auth/key.py
skillpacks/auth/provider.py
skillpacks/auth/transport.py
skillpacks/base.py
skillpacks/chat.py
skillpacks/config.py
skillpacks/db/conn.py
skillpacks/db/models.py
skillpacks/env.py
skillpacks/explore.py
skillpacks/history/__init__.py
skillpacks/history/base.py
skillpacks/img.py
skillpacks/learn/app/dots/learner.py
skillpacks/learn/app/online/learner.py
skillpacks/learn/app/online/test.ipynb
skillpacks/learn/app/ssa/Dockerfile
skillpacks/learn/app/ssa/learner.py
skillpacks/learn/app/test/learner.py
skillpacks/model/base.py
skillpacks/model/qwenvl.py
skillpacks/models/v1alpha/__init__.py
skillpacks/online/__init__.py
skillpacks/online/base.py
skillpacks/online/florence.py
skillpacks/rating.py
skillpacks/review.py
skillpacks/reviewable.py
skillpacks/select/__init__.py
skillpacks/select/base.py
skillpacks/select/gpt4v/__init__.py
skillpacks/select/gpt4v/instruct.py
skillpacks/select/gpt4v/oai.py
skillpacks/select/gpt4v/selector.py
skillpacks/select/qwenvl/instruct.py
skillpacks/select/qwenvl/selector.py
skillpacks/select/util.py
skillpacks/server/models.py
skillpacks/server/routes/action.py
skillpacks/server/routes/episode.py
skillpacks/state.py
skillpacks/task_old.py
skillpacks-0.1.128.dist-info/LICENSE
skillpacks-0.1.128.dist-info/METADATA
skillpacks-0.1.128.dist-info/WHEEL
skillpacks-0.1.128.dist-info/RECORD
