Metadata-Version: 2.1
Name: skillpacks
Version: 0.1.128
Summary: Pluggable skills for AI agents
License: Apache 2.0
Author: Patrick Barker
Author-email: patrickbarkerco@gmail.com
Requires-Python: >=3.10,<4.0
Classifier: License :: Other/Proprietary License
Classifier: Programming Language :: Python :: 3
Classifier: Programming Language :: Python :: 3.10
Classifier: Programming Language :: Python :: 3.11
Classifier: Programming Language :: Python :: 3.12
Requires-Dist: devicebay (>=0.1.28,<0.2.0)
Requires-Dist: mllm (>=0.1.57,<0.2.0)
Requires-Dist: pydantic (>=2.6.1,<3.0.0)
Requires-Dist: shortuuid (>=1.0.13,<2.0.0)
Requires-Dist: sqlalchemy (>=2.0.27,<3.0.0)
